<?xml version="1.0" encoding="UTF-8"?>
<VoidTransportRequestResponse xmlns="http://mws.amazonaws.com/FulfillmentInboundShipment/2010-10-01/">
   <VoidTransportRequestResult>
        <TransportResult>
            <TransportStatus>String</TransportStatus>
            <ErrorCode>String</ErrorCode>
            <ErrorDescription>String</ErrorDescription>
        </TransportResult>
    </VoidTransportRequestResult>
   <ResponseMetadata>
        <RequestId>String</RequestId>
    </ResponseMetadata>
</VoidTransportRequestResponse>
